hydra_vl4ai/__init__.py
hydra_vl4ai/_version.py
hydra_vl4ai/download_model.py
hydra_vl4ai/executor.py
hydra_vl4ai/agent/__init__.py
hydra_vl4ai/agent/controller.py
hydra_vl4ai/agent/hydra.py
hydra_vl4ai/agent/llm.py
hydra_vl4ai/agent/planner.py
hydra_vl4ai/agent/reasoner.py
hydra_vl4ai/agent/rl_dqn.py
hydra_vl4ai/agent/summarizer.py
hydra_vl4ai/agent/webui.py
hydra_vl4ai/agent/prompt/chatgpt-35/gqa/code.prompt
hydra_vl4ai/agent/prompt/chatgpt-35/gqa/code_example.prompt
hydra_vl4ai/agent/prompt/chatgpt-35/gqa/embedding.prompt
hydra_vl4ai/agent/prompt/chatgpt-35/gqa/guess_answer.prompt
hydra_vl4ai/agent/prompt/chatgpt-35/gqa/instruction.prompt
hydra_vl4ai/agent/prompt/chatgpt-35/gqa/instruction_example.prompt
hydra_vl4ai/agent/prompt/chatgpt-35/gqa/summarize.prompt
hydra_vl4ai/agent/prompt/chatgpt-35/gqa/task_description_for_code.prompt
hydra_vl4ai/agent/prompt/chatgpt-35/gqa/task_description_for_instruction.prompt
hydra_vl4ai/agent/prompt/chatgpt-35/okvqa/code.prompt
hydra_vl4ai/agent/prompt/chatgpt-35/okvqa/code_example.prompt
hydra_vl4ai/agent/prompt/chatgpt-35/okvqa/embedding.prompt
hydra_vl4ai/agent/prompt/chatgpt-35/okvqa/guess_answer.prompt
hydra_vl4ai/agent/prompt/chatgpt-35/okvqa/instruction.prompt
hydra_vl4ai/agent/prompt/chatgpt-35/okvqa/instruction_example.prompt
hydra_vl4ai/agent/prompt/chatgpt-35/okvqa/summarize.prompt
hydra_vl4ai/agent/prompt/chatgpt-35/okvqa/task_description_for_code.prompt
hydra_vl4ai/agent/prompt/chatgpt-35/okvqa/task_description_for_instruction.prompt
hydra_vl4ai/agent/prompt/chatgpt-35/refcoco/code.prompt
hydra_vl4ai/agent/prompt/chatgpt-35/refcoco/code_example.prompt
hydra_vl4ai/agent/prompt/chatgpt-35/refcoco/embedding.prompt
hydra_vl4ai/agent/prompt/chatgpt-35/refcoco/instruction.prompt
hydra_vl4ai/agent/prompt/chatgpt-35/refcoco/instruction_example.prompt
hydra_vl4ai/agent/prompt/chatgpt-35/refcoco/task_description_for_code.prompt
hydra_vl4ai/agent/prompt/chatgpt-35/refcoco/task_description_for_instruction.prompt
hydra_vl4ai-0.0.6.dist-info/LICENSE
hydra_vl4ai-0.0.6.dist-info/METADATA
hydra_vl4ai-0.0.6.dist-info/WHEEL
hydra_vl4ai-0.0.6.dist-info/top_level.txt
hydra_vl4ai-0.0.6.dist-info/RECORD
