Metadata-Version: 2.1
Name: hydra-vl4ai
Version: 0.0.6
Summary: Official implementation for HYDRA.
Home-page: https://hydra-vl4ai.github.io/
Author: ControlNet
Author-email: smczx@hotmail.com
Project-URL: Source Code, https://github.com/ControlNet/HYDRA
Project-URL: Bug Tracker, https://github.com/ControlNet/HYDRA/issues
Keywords: deep learning,pytorch,AI
Classifier: Programming Language :: Python :: 3
Classifier: Programming Language :: Python :: 3.10
Classifier: Programming Language :: Python :: 3.11
Classifier: Programming Language :: Python :: 3.12
Classifier: License :: OSI Approved :: Apache Software License
Classifier: Operating System :: OS Independent
Classifier: Intended Audience :: Developers
Classifier: Topic :: Scientific/Engineering :: Artificial Intelligence
Requires-Python: >=3.10
License-File: LICENSE
Requires-Dist: torch
Requires-Dist: fastapi
Requires-Dist: uvicorn
Requires-Dist: starlette
Requires-Dist: openai
Requires-Dist: websockets
Requires-Dist: tensorneko-util<0.4.0,>=0.3.21
Requires-Dist: requests
Requires-Dist: pillow
Requires-Dist: word2number
Requires-Dist: ollama
Requires-Dist: bitsandbytes
Requires-Dist: numpy<2
Requires-Dist: gradio<5.12,>=5.0
Requires-Dist: pydantic<2.11
Requires-Dist: python-dotenv
Requires-Dist: transformers
Requires-Dist: opencv-python
Requires-Dist: rich
